ujson5/__init__.py
ujson5/__version__.py
ujson5/cli.py
ujson5/consts.py
ujson5/core.py
ujson5/decoder.py
ujson5/encoder.py
ujson5/err_msg.py
ujson5/lexer.py
ujson5-1.0.1.dist-info/METADATA
ujson5-1.0.1.dist-info/WHEEL
ujson5-1.0.1.dist-info/entry_points.txt
ujson5-1.0.1.dist-info/licenses/LICENSE
ujson5-1.0.1.dist-info/RECORD
